afpgvector/__init__.py
afpgvector/admin.py
afpgvector/apps.py
afpgvector/models.py
afpgvector/settings.py
django_afpgvector-0.0.1.dist-info/METADATA
django_afpgvector-0.0.1.dist-info/WHEEL
django_afpgvector-0.0.1.dist-info/top_level.txt
django_afpgvector-0.0.1.dist-info/RECORD
