Metadata-Version: 2.1
Name: django-afpgvector
Version: 0.0.1
Summary: Package for handling postgres vector database
Home-page: https://github.com/aosfatos/django-afpgvector/
Author: Aos Fatos
Author-email: aosfatos@aosfatos.org
License: GNU Lesser General Public License v3 (LGPLv3)
Keywords: vector database embedding
Classifier: Environment :: Web Environment
Classifier: Framework :: Django
Classifier: Framework :: Django :: 3.2
Classifier: Intended Audience :: Developers
Classifier: License :: OSI Approved :: GNU Lesser General Public License v3 (LGPLv3)
Classifier: Operating System :: OS Independent
Classifier: Programming Language :: Python
Classifier: Programming Language :: Python :: 3
Classifier: Programming Language :: Python :: 3 :: Only
Classifier: Programming Language :: Python :: 3.6
Classifier: Programming Language :: Python :: 3.7
Classifier: Programming Language :: Python :: 3.8
Classifier: Topic :: Internet :: WWW/HTTP
Classifier: Topic :: Internet :: WWW/HTTP :: Dynamic Content
Requires-Python: >=3.7
Requires-Dist: Django >=3.2.0
Requires-Dist: pgvector ==0.2.5
